yamllint/__init__.py
yamllint/__main__.py
yamllint/cli.py
yamllint/config.py
yamllint/linter.py
yamllint/parser.py
yamllint/conf/default.yaml
yamllint/conf/relaxed.yaml
yamllint/rules/__init__.py
yamllint/rules/anchors.py
yamllint/rules/braces.py
yamllint/rules/brackets.py
yamllint/rules/colons.py
yamllint/rules/commas.py
yamllint/rules/comments.py
yamllint/rules/comments_indentation.py
yamllint/rules/common.py
yamllint/rules/document_end.py
yamllint/rules/document_start.py
yamllint/rules/empty_lines.py
yamllint/rules/empty_values.py
yamllint/rules/float_values.py
yamllint/rules/hyphens.py
yamllint/rules/indentation.py
yamllint/rules/key_duplicates.py
yamllint/rules/key_ordering.py
yamllint/rules/line_length.py
yamllint/rules/new_line_at_end_of_file.py
yamllint/rules/new_lines.py
yamllint/rules/octal_values.py
yamllint/rules/quoted_strings.py
yamllint/rules/trailing_spaces.py
yamllint/rules/truthy.py
yamllint-1.36.1.dist-info/LICENSE
yamllint-1.36.1.dist-info/METADATA
yamllint-1.36.1.dist-info/WHEEL
yamllint-1.36.1.dist-info/entry_points.txt
yamllint-1.36.1.dist-info/top_level.txt
yamllint-1.36.1.dist-info/RECORD
