Metadata-Version: 2.2
Name: yamllint
Version: 1.36.1
Summary: A linter for YAML files.
Author: Adrien Vergé
License: GPL-3.0-or-later
Project-URL: homepage, https://github.com/adrienverge/yamllint
Project-URL: repository, https://github.com/adrienverge/yamllint
Project-URL: documentation, https://yamllint.readthedocs.io
Keywords: yaml,lint,linter,syntax,checker
Classifier: Development Status :: 5 - Production/Stable
Classifier: Environment :: Console
Classifier: Intended Audience :: Developers
Classifier: License :: OSI Approved :: GNU General Public License v3 (GPLv3)
Classifier: Programming Language :: Python
Classifier: Topic :: Software Development
Classifier: Topic :: Software Development :: Debuggers
Classifier: Topic :: Software Development :: Quality Assurance
Classifier: Topic :: Software Development :: Testing
Requires-Python: >=3.9
License-File: LICENSE
Requires-Dist: pathspec>=0.5.3
Requires-Dist: pyyaml
Provides-Extra: dev
Requires-Dist: doc8; extra == "dev"
Requires-Dist: flake8; extra == "dev"
Requires-Dist: flake8-import-order; extra == "dev"
Requires-Dist: rstcheck[sphinx]; extra == "dev"
Requires-Dist: sphinx; extra == "dev"
